{"type": "Feature", "id": 12517351, "properties": {"woe:id": 12517351, "woe:parent_id": 1939887, "woe:name": "Kp 718 Airport", "woe:placetype": 14, "woe:placetype_name": "Airport", "woe:lang": "ENG", "iso:country": "SA", "meta:provider": ["geoplanet:7.3.1", "geoplanet:7.3.2", "geoplanet:7.4.0", "geoplanet:7.4.1", "geoplanet:7.5.1", "geoplanet:7.5.2", "geoplanet:7.6.0", "geoplanet:7.8.1", "geoplanet:7.9.0", "geoplanet:7.10.0", "geoplanet:8.0.0", "woeplanet:8.0.0"], "meta:indexed": "2020-08-20T20:21:16.153711", "meta:updated": "2020-08-22T02:50:21.031723", "woe:hierarchy": {"continent": 24865671, "country": 23424938, "town": 0, "planet": 1, "county": 56120188, "suburb": 0, "state": 2346951, "region": 0, "localadmin": 0}, "woe:timezone_id": 28350851, "woe:hash": "th2hsm59dfjc", "woe:centroid": [45.1917, 24.725], "geom:latitude": 24.725, "geom:longitude": 45.1917, "geom:hash": "th2hsm59dfjc", "woe:latitude": 24.725, "geom:centroid": [45.1917, 24.725], "woe:longitude": 45.1917, "woe:repo": "woeplanet-airport-sa"}, "geometry": {"coordinates": [45.1917, 24.725], "type": "Point"}}