{"type": "Feature", "id": 12517325, "geometry": {"type": "Point", "coordinates": [47.417198, 24.0644]}, "properties": {"woe:id": 12517325, "woe:parent_id": 1938274, "woe:name": "Al Kharj Airport", "woe:placetype": 14, "woe:placetype_name": "Airport", "woe:lang": "ENG", "iso:country": "SA", "meta:provider": ["geoplanet:7.3.1", "geoplanet:7.3.2", "geoplanet:7.4.0", "geoplanet:7.4.1", "geoplanet:7.5.1", "geoplanet:7.5.2", "geoplanet:7.6.0", "geoplanet:7.8.1", "geoplanet:7.9.0", "geoplanet:7.10.0", "geoplanet:8.0.0", "woeplanet:8.0.0"], "meta:indexed": "2020-08-20T20:21:16.133434", "woe:alias_ENG_V": ["AKH Airport", "AKH"], "meta:updated": "2020-10-14T11:18:03.959560", "woe:hierarchy": {"continent": 24865671, "country": 23424938, "town": 0, "planet": 1, "county": 56120177, "suburb": 0, "state": 2346951, "region": 0, "localadmin": 0}, "woe:timezone_id": 28350851, "woe:hash": "th38zhb1kc33", "woe:centroid": [47.417198, 24.0644], "geom:latitude": 24.0644, "geom:longitude": 47.417198, "geom:hash": "th38zhb1kc33", "woe:latitude": 24.0644, "geom:centroid": [47.417198, 24.0644], "woe:longitude": 47.417198, "woe:repo": "woeplanet-airport-sa", "geom:area": 0.0, "woe:scale": 19}}