{"type": "Feature", "id": 12517344, "geometry": {"type": "Point", "coordinates": [46.3978, 24.948601]}, "properties": {"woe:id": 12517344, "woe:parent_id": 1937693, "woe:name": "King Abdul Aziz Military Academy Airport", "woe:placetype": 14, "woe:placetype_name": "Airport", "woe:lang": "ENG", "iso:country": "SA", "meta:provider": ["geoplanet:7.3.1", "geoplanet:7.3.2", "geoplanet:7.4.0", "geoplanet:7.4.1", "geoplanet:7.5.1", "geoplanet:7.5.2", "geoplanet:7.6.0", "geoplanet:7.8.1", "geoplanet:7.9.0", "geoplanet:7.10.0", "geoplanet:8.0.0", "woeplanet:8.0.0"], "meta:indexed": "2020-08-20T20:21:16.148210", "meta:updated": "2020-10-14T11:18:03.978675", "woe:hierarchy": {"continent": 24865671, "country": 23424938, "town": 0, "planet": 1, "county": 56120193, "suburb": 0, "state": 2346951, "region": 0, "localadmin": 0}, "woe:timezone_id": 28350851, "woe:hash": "th2vzvcb5h71", "woe:centroid": [46.3978, 24.948601], "geom:latitude": 24.948601, "geom:longitude": 46.3978, "geom:hash": "th2vzvcb5h71", "woe:latitude": 24.948601, "geom:centroid": [46.3978, 24.948601], "woe:longitude": 46.3978, "woe:repo": "woeplanet-airport-sa", "geom:area": 0.0, "woe:scale": 19}}